{"0810": {"desc": "NON-CONVENTIONAL SOURCES OF ENERGY", "102": {"desc": "Solar", "AC": {"desc": "Receipts from Ministry of New and Renewable Energy for Solar Power Pumping System linked with appropriate Micro Irrigation System (Drip/Sprinklers/Mini Sprinklers) [0506]", "221": {"desc": "Receipts from Central Government", "2018": "", "2019Est": "8,50,00", "2019Rev": "18,76,75", "2020Est": "1", "99": {"desc": "Others", "2018": "", "2019Est": "8,50,00", "2019Rev": "18,76,75", "2020Est": "1"}}, "Total AC": {"2018": "", "2019Est": "8,50,00", "2019Rev": "18,76,75", "2020Est": "1"}}, "Total 102": {"2018": "", "2019Est": "8,50,00", "2019Rev": "18,76,75", "2020Est": "1"}}, "800": {"desc": "Other Receipts", "AA": {"desc": "Other Receipts [2704]", "290": {"desc": "Miscellaneous Revenue Receipts", "2018": "68,93", "2019Est": "1", "2019Rev": "1", "2020Est": "1", "01": {"desc": "Miscellaneous Receipts", "2018": "68,93", "2019Est": "1", "2019Rev": "1", "2020Est": "1"}}, "Total AA": {"2018": "68,93", "2019Est": "1", "2019Rev": "1", "2020Est": "1"}}, "Total 800": {"2018": "68,93", "2019Est": "1", "2019Rev": "1", "2020Est": "1"}}, "Total 0810": {"2018": "68,93", "2019Est": "8,50,01", "2019Rev": "18,76,76", "2020Est": "2"}}}